{
  "channels": [
    { "name": "Sky Sport 1 HD", "id": 403251, "region": "NZ", "category": "sport" },
    { "name": "Sky Sport 2 HD", "id": 403256, "region": "NZ", "category": "sport" },
    { "name": "Sky Sport 3 HD", "id": 403252, "region": "NZ", "category": "sport" },
    { "name": "Sky Sport 4 HD", "id": 403248, "region": "NZ", "category": "sport" },
    { "name": "Sky Sport 5 HD", "id": 403249, "region": "NZ", "category": "sport" },
    { "name": "Sky Sport 6 HD", "id": 403250, "region": "NZ", "category": "sport" },
    { "name": "Sky Sports + UK", "id": 412959, "region": "UK", "category": "sport" },
    { "name": "Sky Sports Premier League UK", "id": 6958, "region": "UK", "category": "sport" },
    { "name": "Sky Sports News UK", "id": 6626, "region": "UK", "category": "sport" },
    { "name": "BBC One UK", "id": 486880, "region": "UK", "category": "entertainment" },
    { "name": "BBC Two UK", "id": 486673, "region": "UK", "category": "entertainment" },
    { "name": "BBC Three UK", "id": 486878, "region": "UK", "category": "entertainment" },
    { "name": "BBC News UK", "id": 12162, "region": "UK", "category": "news" },
    { "name": "GB News UK", "id": 12133, "region": "UK", "category": "news" },
    { "name": "Sky News UK", "id": 12069, "region": "UK", "category": "news" },
    { "name": "ESPN US", "id": 465198, "region": "US", "category": "sport" },
    { "name": "ESPN News US", "id": 417108, "region": "US", "category": "sport" },
    { "name": "ESPN2 US", "id": 465373, "region": "US", "category": "sport" },
    { "name": "ESPN U US", "id": 417125, "region": "US", "category": "sport" },
    { "name": "NBA TV US", "id": 406263, "region": "US", "category": "sport" },
    { "name": "NFL Network US", "id": 454083, "region": "US", "category": "sport" },
    { "name": "Animal Planet US", "id": 465310, "region": "US", "category": "entertainment" },
    { "name": "Cartoon Network US", "id": 464853, "region": "US", "category": "entertainment" },
    { "name": "Comedy Central US", "id": 464922, "region": "US", "category": "entertainment" },
    { "name": "Discovery Channel US", "id": 465364, "region": "US", "category": "entertainment" },
    { "name": "HBO Comedy US", "id": 464953, "region": "US", "category": "entertainment" },
    { "name": "Nickelodeon US", "id": 465251, "region": "US", "category": "entertainment" },
    { "name": "TNT US", "id": 465114, "region": "US", "category": "entertainment", "source": "epg.pw" },
    { "name": "MSNBC US", "id": 464889, "region": "US", "category": "news", "source": "epg.pw" },
    { "name": "FOX League", "xmlid": "SP2", "region": "AU", "category": "sport", "source": "xmltv", "url": "https://raw.githubusercontent.com/matthuisman/i.mjh.nz/refs/heads/master/Foxtel/epg.xml" }
  ]
}
